{
  "content": [
    {
      "content": null,
      "created": "2022-03-22T00:33:22.625890Z",
      "format": null,
      "last_modified": "2022-03-22T00:25:02.162462Z",
      "mimetype": null,
      "name": "notifications.ipynb",
      "path": "panel/reference/state/notifications.ipynb",
      "size": 6483,
      "type": "notebook",
      "writable": true
    },
    {
      "content": null,
      "created": "2022-03-22T00:33:22.632416Z",
      "format": null,
      "last_modified": "2022-03-22T00:25:02.227386Z",
      "mimetype": null,
      "name": "schedule.ipynb",
      "path": "panel/reference/state/schedule.ipynb",
      "size": 7490253,
      "type": "notebook",
      "writable": true
    },
    {
      "content": null,
      "created": "2022-03-22T00:33:22.624868Z",
      "format": null,
      "last_modified": "2022-03-22T00:25:02.228103Z",
      "mimetype": null,
      "name": "as_cached.ipynb",
      "path": "panel/reference/state/as_cached.ipynb",
      "size": 300,
      "type": "notebook",
      "writable": true
    },
    {
      "content": null,
      "created": "2022-03-22T00:33:22.624053Z",
      "format": null,
      "last_modified": "2022-03-22T00:25:02.337694Z",
      "mimetype": null,
      "name": "add_periodic_callback.ipynb",
      "path": "panel/reference/state/add_periodic_callback.ipynb",
      "size": 14991123,
      "type": "notebook",
      "writable": true
    },
    {
      "content": null,
      "created": "2022-03-22T00:33:22.625372Z",
      "format": null,
      "last_modified": "2022-03-22T00:25:02.338371Z",
      "mimetype": null,
      "name": "location.ipynb",
      "path": "panel/reference/state/location.ipynb",
      "size": 300,
      "type": "notebook",
      "writable": true
    },
    {
      "content": null,
      "created": "2022-03-22T00:33:22.626359Z",
      "format": null,
      "last_modified": "2022-03-22T00:25:02.338780Z",
      "mimetype": null,
      "name": "onload.ipynb",
      "path": "panel/reference/state/onload.ipynb",
      "size": 933,
      "type": "notebook",
      "writable": true
    }
  ],
  "created": "2022-03-22T00:33:22.626568Z",
  "format": "json",
  "last_modified": "2022-03-22T00:33:22.626568Z",
  "mimetype": null,
  "name": "state",
  "path": "panel/reference/state",
  "size": null,
  "type": "directory",
  "writable": true
}